<?xml version="1.0" encoding="ISO-8859-1"?>



<options>
 <gui>
  <headertable> 
    <headeritem>
      <name>Status</name> 
      <position>0</position> 
      <size>23</size> 
      <enabled>true</enabled> 
    </headeritem> 
    <headeritem> 
      <name>Attachment</name> 
      <position>1</position> 
      <size>23</size> 
      <enabled>true</enabled> 
    </headeritem> 
    <headeritem> 
      <name>Flagged</name> 
      <position>1</position> 
      <size>23</size> 
      <enabled>true</enabled> 
    </headeritem> 
    <headeritem> 
      <name>Priority</name> 
      <position>2</position> 
      <size>23</size> 
      <enabled>true</enabled> 
    </headeritem> 
    <headeritem> 
      <name>Subject</name> 
      <position>3</position> 
      <size>196</size> 
      <enabled>true</enabled> 
    </headeritem> 
    <headeritem> 
      <name>From</name> 
      <position>4</position> 
      <size>146</size> 
      <enabled>true</enabled> 
    </headeritem> 
    <headeritem> 
      <name>Date</name> 
      <position>5</position> 
      <size>146</size> 
      <enabled>true</enabled> 
    </headeritem> 
    <headeritem> 
      <name>Size</name> 
      <position>6</position> 
      <size>97</size> 
      <enabled>true</enabled> 
    </headeritem> 
    <headeritem> 
      <name>To</name> 
      <position>7</position> 
      <size>100</size> 
      <enabled>false</enabled> 
    </headeritem> 
    <headeritem> 
      <name>Cc</name> 
      <position>8</position> 
      <size>100</size> 
      <enabled>false</enabled> 
    </headeritem> 
    <headeritem> 
	<name>Bcc</name> 
	<position>9</position> 
	<size>100</size> 
	<enabled>false</enabled> 
      </headeritem> 
    <headeritem> 
	<name>Message-ID</name> 
	<position>10</position> 
	<size>100</size> 
	<enabled>false</enabled> 
      </headeritem> 
      <headeritem> 
	<name>In-Reply-To</name> 
	<position>11</position> 
	<size>100</size> 
	<enabled>false</enabled> 
      </headeritem> 
      <headeritem> 
	<name>References</name> 
	<position>12</position> 
	<size>100</size> 
	<enabled>false</enabled> 
      </headeritem>
      <headeritem> 
	<name>Content-Type</name> 
	<position>13</position> 
	<size>100</size> 
	<enabled>false</enabled> 
      </headeritem>
  </headertable>
  <window> 
    <xposition>0</xposition> 
    <yposition>0</yposition> 
    <width>900</width> 
    <height>800</height> 
    <showfiltertoolbar>true</showfiltertoolbar> 
    <showtoolbar>true</showtoolbar> 
    <showfolderinfo>true</showfolderinfo> 
    <mainsplitpane>100</mainsplitpane>
    <headersplitpane>100</headersplitpane>
    <attachmentsplitpane>100</attachmentsplitpane>
    <selectedheader>Date</selectedheader>
    <headerascending>true</headerascending>    
    <advancedviewer>true</advancedviewer>
    <htmlviewer>true</htmlviewer>
  </window> 
 </gui>
</options>

